Assemble-0.2.2.dist-info/DESCRIPTION.rst
Assemble-0.2.2.dist-info/METADATA
Assemble-0.2.2.dist-info/RECORD
Assemble-0.2.2.dist-info/WHEEL
Assemble-0.2.2.dist-info/entry_points.txt
Assemble-0.2.2.dist-info/metadata.json
Assemble-0.2.2.dist-info/top_level.txt
assemble/__init__.py
assemble/assemble.py
assemble/cli.py
assemble/requirements.py
assemble/utils.py
