Metadata-Version: 2.0
Name: Assemble
Version: 0.2.2
Summary: Assemble: Assemble the packages!
Home-page: https://github.com/CorverDevelopment/Assemble/
Author: Nils Corver
Author-email: nils@corverdevelopment.nl
License: MIT
Keywords: routing
Platform: UNKNOWN
Classifier: Development Status :: 3 - Alpha
Classifier: Intended Audience :: Developers
Classifier: Natural Language :: English
Classifier: License :: OSI Approved :: MIT License
Classifier: Operating System :: OS Independent
Classifier: Programming Language :: Python
Classifier: Programming Language :: Python :: 2
Classifier: Programming Language :: Python :: 2.7
Classifier: Programming Language :: Python :: 3
Classifier: Programming Language :: Python :: 3.5
Classifier: Programming Language :: Python :: Implementation :: CPython
Classifier: Topic :: Software Development :: Libraries :: Python Modules
Requires-Dist: click (>=6.3)
Requires-Dist: pip (>=8.1.1)
Requires-Dist: python-Levenshtein (>=0.12.0)
Requires-Dist: setuptools (>=20.2.2)
